siTOOgether/__init__.py
siTOOgether/main.py
sitoogether-0.0.4.dist-info/METADATA
sitoogether-0.0.4.dist-info/WHEEL
sitoogether-0.0.4.dist-info/entry_points.txt
sitoogether-0.0.4.dist-info/top_level.txt
sitoogether-0.0.4.dist-info/RECORD
